espm/__init__.py
espm/conf.py
espm/hyperspy_extension.yaml
espm/measures.py
espm/tables_utils.py
espm/utils.py
espm/datasets/__init__.py
espm/datasets/base.py
espm/datasets/built_in_EDXS_datasets.py
espm/datasets/eds_spim.py
espm/datasets/eds_spim_sim.py
espm/datasets/toy-problem/phase1.png
espm/datasets/toy-problem/phase2.png
espm/datasets/toy-problem/phase1.pxd/metadata.info
espm/datasets/toy-problem/phase1.pxd/QuickLook/Icon.tiff
espm/datasets/toy-problem/phase1.pxd/QuickLook/Thumbnail.tiff
espm/datasets/toy-problem/phase1.pxd/data/3621E7F2-72F0-4D2E-AFAE-7E2BF95C0863
espm/datasets/toy-problem/phase2.pxd/metadata.info
espm/datasets/toy-problem/phase2.pxd/QuickLook/Icon.tiff
espm/datasets/toy-problem/phase2.pxd/QuickLook/Thumbnail.tiff
espm/datasets/toy-problem/phase2.pxd/data/3D5861EE-4BAE-4F2E-8CA2-FCA3A51D8FDF
espm/datasets/toy-problem/phase2.pxd/data/AA0EA8B3-ADF5-44EE-8AD9-50E7DD8D6285
espm/datasets/toy-problem/phase2.pxd/data/selection/meta
espm/datasets/toy-problem/phase2.pxd/data/selection/shapeSelection/meta
espm/datasets/toy-problem/phase2.pxd/data/selection/shapeSelection/path
espm/estimators/__init__.py
espm/estimators/base.py
espm/estimators/dicotomy.py
espm/estimators/smooth_nmf.py
espm/estimators/surrogates.py
espm/estimators/updates.py
espm/models/EDXS_function.py
espm/models/__init__.py
espm/models/absorption_edxs.py
espm/models/base.py
espm/models/edxs.py
espm/models/generate_EDXS_phases.py
espm/tables/100keV_xrays.json
espm/tables/200keV_xrays.json
espm/tables/300keV_xrays.json
espm/tables/SDD_efficiency.txt
espm/tables/__init__.py
espm/tables/default_xrays.json
espm/tables/periodic_table_number.json
espm/tables/periodic_table_symbols.json
espm/tables/siegbahn_to_iupac.json
espm/tests/__init__.py
espm/tests/test_EDXS.py
espm/tests/test_datasets.py
espm/tests/test_docstring.py
espm/tests/test_estimators.py
espm/tests/test_laplacian.py
espm/tests/test_measures.py
espm/tests/test_updates.py
espm/tests/test_utils.py
espm/weights/__init__.py
espm-1.1.3.dist-info/Licence.txt
espm-1.1.3.dist-info/METADATA
espm-1.1.3.dist-info/WHEEL
espm-1.1.3.dist-info/entry_points.txt
espm-1.1.3.dist-info/top_level.txt
espm-1.1.3.dist-info/RECORD
