Metadata-Version: 2.2
Name: espm
Version: 1.1.3
Summary: Electron SPectro-Microscopy Python Library
License: Copyright 2022-2023 Adrien Teurtrie and Nathanael Perraudin
Project-URL: Homepage, https://espm.readthedocs.io/en/latest/
Project-URL: Bug Reports, https://github.com/adriente/espm/issues
Project-URL: Source, https://github.com/adriente/espm
Keywords: python,data analysis,microscopy,electron microscopy,energy-dispersive X-ray spectroscopy,X-ray energy-dispersive spectroscopy,EDS,EDX,STEM
Classifier: Development Status :: 5 - Production/Stable
Classifier: Intended Audience :: Science/Research
Classifier: Intended Audience :: End Users/Desktop
Classifier: Intended Audience :: Developers
Classifier: Natural Language :: English
Classifier: License :: OSI Approved :: GNU General Public License v3 (GPLv3)
Classifier: Operating System :: MacOS :: MacOS X
Classifier: Operating System :: POSIX :: Linux
Classifier: Programming Language :: C
Classifier: Programming Language :: Python :: 3.10
Classifier: Programming Language :: Python :: 3.9
Classifier: Programming Language :: Python :: 3.8
Classifier: Topic :: Scientific/Engineering :: Mathematics
Classifier: Topic :: Scientific/Engineering
Requires-Python: >=3.8
License-File: Licence.txt
Requires-Dist: exspy==0.3.1
Requires-Dist: hyperspy==2.2.0
Requires-Dist: hyperspy-gui-ipywidgets==2.0.3
Requires-Dist: hyperspy-gui-traitsui==2.0.1
Requires-Dist: intervaltree==3.1.0
Requires-Dist: tqdm==4.67.0
Requires-Dist: prettytable==3.12.0
Requires-Dist: scikit-learn
Requires-Dist: pyqt5==5.15.10
Requires-Dist: traits==7.0.2
Provides-Extra: dev
Requires-Dist: numpydoc; extra == "dev"
Requires-Dist: flake8; extra == "dev"
Requires-Dist: sphinx; extra == "dev"
Requires-Dist: setuptools; extra == "dev"
Requires-Dist: jupyterlab; extra == "dev"
Requires-Dist: wheel; extra == "dev"
Requires-Dist: sphinxcontrib-bibtex; extra == "dev"
Requires-Dist: memory_profiler; extra == "dev"
Requires-Dist: sphinx-rtd-theme; extra == "dev"
Requires-Dist: sphinx-copybutton; extra == "dev"
Requires-Dist: sphinx-gallery; extra == "dev"
Requires-Dist: nbsphinx; extra == "dev"
Requires-Dist: pandoc; extra == "dev"
Requires-Dist: pytest; extra == "dev"
